bloxlink/__init__.py
bloxlink/client.py
bloxlink/exception.py
bloxlink/payload.py
bloxlink/objects/__init__.py
bloxlink/objects/discorduser.py
bloxlink/objects/response.py
bloxlink/objects/robloxuser.py
pybloxlink-1.0.0.dist-info/LICENSE.txt
pybloxlink-1.0.0.dist-info/METADATA
pybloxlink-1.0.0.dist-info/WHEEL
pybloxlink-1.0.0.dist-info/top_level.txt
pybloxlink-1.0.0.dist-info/RECORD
