Metadata-Version: 2.1
Name: pybloxlink
Version: 1.0.0
Summary: An API wrapper for the Bloxlink API.
Author: acatia
License: The MIT License (MIT)
Project-URL: Documentation, https://acatiadroid.github.io/pybloxlink
Project-URL: GitHub, https://github.com/acatiadroid/pybloxlink
Classifier: Development Status :: 5 - Production/Stable
Classifier: Intended Audience :: Developers
Classifier: Programming Language :: Python :: 3
Classifier: Operating System :: Unix
Classifier: Operating System :: MacOS :: MacOS X
Classifier: Operating System :: Microsoft :: Windows
Requires-Python: >=3.8
License-File: LICENSE.txt
